LICENSE.txt
README.md
setup.cfg
setup.py
SAMBA_ilum_3.egg-info/PKG-INFO
SAMBA_ilum_3.egg-info/SOURCES.txt
SAMBA_ilum_3.egg-info/dependency_links.txt
SAMBA_ilum_3.egg-info/entry_points.txt
SAMBA_ilum_3.egg-info/requires.txt
SAMBA_ilum_3.egg-info/top_level.txt
samba_ilum_3/__init__.py
samba_ilum_3/__main__.py
samba_ilum_3/src/BZ_2D.py
samba_ilum_3/src/HeteroStructure_Generator.py
samba_ilum_3/src/_info_pseudo.py
samba_ilum_3/src/a-scan.py
samba_ilum_3/src/a-scan_analysis.py
samba_ilum_3/src/bader
samba_ilum_3/src/bader_poscar.py
samba_ilum_3/src/bader_update.py
samba_ilum_3/src/charge_transfer.py
samba_ilum_3/src/chgsum.pl
samba_ilum_3/src/contcar_update.py
samba_ilum_3/src/data-base_json.py
samba_ilum_3/src/data-base_union.py
samba_ilum_3/src/energy_scan.py
samba_ilum_3/src/hubbard_correction.py
samba_ilum_3/src/job.py
samba_ilum_3/src/kpoints.py
samba_ilum_3/src/lattice_plot3d.py
samba_ilum_3/src/make_files.py
samba_ilum_3/src/output.py
samba_ilum_3/src/potcar.py
samba_ilum_3/src/vdW_DF.py
samba_ilum_3/src/xy-scan.py
samba_ilum_3/src/xy-scan_analysis.py
samba_ilum_3/src/xyz-scan.py
samba_ilum_3/src/xyz-scan_analysis.py
samba_ilum_3/src/z-scan.py
samba_ilum_3/src/z-scan_analysis.py
samba_ilum_3/src/INPUTS/INCAR_a-scan
samba_ilum_3/src/INPUTS/INCAR_bader
samba_ilum_3/src/INPUTS/INCAR_bader.SO
samba_ilum_3/src/INPUTS/INCAR_bands
samba_ilum_3/src/INPUTS/INCAR_bands.SO
samba_ilum_3/src/INPUTS/INCAR_dos
samba_ilum_3/src/INPUTS/INCAR_dos.SO
samba_ilum_3/src/INPUTS/INCAR_relax
samba_ilum_3/src/INPUTS/INCAR_scf
samba_ilum_3/src/INPUTS/INCAR_scf.SO
samba_ilum_3/src/INPUTS/INCAR_xy-scan
samba_ilum_3/src/INPUTS/INCAR_xyz-scan
samba_ilum_3/src/INPUTS/INCAR_z-scan
samba_ilum_3/src/INPUTS/SAMBA_HeteroStructure.input
samba_ilum_3/src/INPUTS/SAMBA_WorkFlow.input
samba_ilum_3/src/INPUTS/vdw_kernel.bindat
samba_ilum_3/src/INPUTS/inputs_VASProcar/input.vasprocar.bands
samba_ilum_3/src/INPUTS/inputs_VASProcar/input.vasprocar.chgcar
samba_ilum_3/src/INPUTS/inputs_VASProcar/input.vasprocar.dos
samba_ilum_3/src/INPUTS/inputs_VASProcar/input.vasprocar.location
samba_ilum_3/src/INPUTS/inputs_VASProcar/input.vasprocar.locpot
samba_ilum_3/src/INPUTS/inputs_VASProcar/input.vasprocar.orbitals
