Metadata-Version: 2.1
Name: SAMBA_ilum_3
Version: 1.0.0.3
Summary: ...
Author: Augusto de Lelis Araujo
Author-email: augusto-lelis@outlook.com
License: Closed source
License-File: LICENSE.txt
Requires-Dist: matplotlib
Requires-Dist: pymatgen
Requires-Dist: pyfiglet
Requires-Dist: requests
Requires-Dist: plotly
Requires-Dist: scipy
Requires-Dist: numpy
Requires-Dist: uuid
Requires-Dist: vasprocar
